netx_vis/__init__.py
netx_vis/converter.py
netx_vis/templates/graph_template.html
netx_vis-0.2.6.dist-info/licenses/LICENSE
tests/__init__.py
tests/test_converter.py
netx_vis-0.2.6.dist-info/METADATA
netx_vis-0.2.6.dist-info/WHEEL
netx_vis-0.2.6.dist-info/top_level.txt
netx_vis-0.2.6.dist-info/RECORD
