Metadata-Version: 2.4
Name: netx-vis
Version: 0.2.6
Summary: Convert NetworkX graphs to interactive HTML visualizations
Home-page: https://github.com/olsihoxha/netx-vis
Author: Olsi
Project-URL: Bug Tracker, https://github.com/olsihoxha/netx-vis/issues
Project-URL: Documentation, https://github.com/olsihoxha/netx-vis#readme
Project-URL: Source Code, https://github.com/olsihoxha/netx-vis
Keywords: networkx,graph,visualization,html,interactive,d3js,network,graph-analysis,data-visualization
Classifier: Development Status :: 5 - Production/Stable
Classifier: Intended Audience :: Developers
Classifier: Intended Audience :: Science/Research
Classifier: Topic :: Scientific/Engineering :: Visualization
Classifier: Topic :: Software Development :: Libraries :: Python Modules
Classifier: License :: OSI Approved :: MIT License
Classifier: Programming Language :: Python :: 3
Classifier: Programming Language :: Python :: 3.7
Classifier: Programming Language :: Python :: 3.8
Classifier: Programming Language :: Python :: 3.9
Classifier: Programming Language :: Python :: 3.10
Classifier: Programming Language :: Python :: 3.11
Classifier: Programming Language :: JavaScript
Classifier: Operating System :: OS Independent
Requires-Python: >=3.7
License-File: LICENSE
Requires-Dist: networkx>=2.5
Requires-Dist: setuptools>=40.0
Dynamic: author
Dynamic: classifier
Dynamic: description
Dynamic: description-content-type
Dynamic: home-page
Dynamic: keywords
Dynamic: license-file
Dynamic: project-url
Dynamic: requires-dist
Dynamic: requires-python
Dynamic: summary
